wikimuscle/__init__.py
wikimuscle/apiwiki.py
wikimuscle/categories_url.py
wikimuscle/config.py
wikimuscle/interfaces.py
wikimuscle/services.py
wikimuscle-1.0.0.dist-info/METADATA
wikimuscle-1.0.0.dist-info/WHEEL
wikimuscle-1.0.0.dist-info/top_level.txt
wikimuscle-1.0.0.dist-info/RECORD
