Metadata-Version: 2.1
Name: wikimuscle
Version: 1.0.0
Summary: API non officiel de wikimuscle
Home-page: https://gitlab.com/misternobody01/wikimusclesapi.git
Author: personne monsieur
Author-email: monsieurnobody01@gmail.com
Classifier: Programming Language :: Python :: 3
Classifier: License :: OSI Approved :: MIT License
Classifier: Operating System :: OS Independent
Requires-Python: >=3.6
Requires-Dist: requests==2.32.3
